EasyPyE/__init__.py
EasyPyE/main.py
EasyPyE-0.1.0.dist-info/METADATA
EasyPyE-0.1.0.dist-info/WHEEL
EasyPyE-0.1.0.dist-info/top_level.txt
EasyPyE-0.1.0.dist-info/RECORD
