Metadata-Version: 2.1
Name: EasyPyE
Version: 0.1.0
Summary: EasyPyE
Home-page: 
Author: ThePyGuy
Author-email: ThePyGuyTeam@gmail.com
Classifier: Intended Audience :: Developers
Classifier: License :: OSI Approved :: MIT License
Classifier: Programming Language :: Python
Classifier: Programming Language :: Python :: 3
Classifier: Programming Language :: Python :: 3.6
Classifier: Programming Language :: Python :: 3.7
Classifier: Programming Language :: Python :: 3.8
Classifier: Programming Language :: Python :: 3.9
Classifier: Operating System :: OS Independent
Requires-Dist: colorama
